csntm_toolbox/__init__.py
csntm_toolbox-0.1.0.dist-info/WHEEL
csntm_toolbox-0.1.0.dist-info/METADATA
csntm_toolbox-0.1.0.dist-info/RECORD
