Metadata-Version: 2.1
Name: csntm-toolbox
Version: 0.1.0
Summary: 
Author: David Flood
Author-email: davidfloodii@gmail.com
Requires-Python: >=3.10,<4.0
Classifier: Programming Language :: Python :: 3
Classifier: Programming Language :: Python :: 3.10
Requires-Dist: ManuscriptMonitor (>=0.1.0,<0.2.0)
Requires-Dist: NameWiz (>=0.1.0,<0.2.0)
Requires-Dist: prepify (>=0.5.0,<0.6.0)
